{
	"types": [{
		"id": 1,
		"chart_pref_x": 0.5,
		"chart_pref_y": 0.0,
		"color": "#E57373",
		"name": "prereqs"
	}, {
		"id": 2,
		"chart_pref_x": 1.0,
		"chart_pref_y": -0.2,
		"color": "#FFF176",
		"name": "core"
	}, {
		"id": 3,
		"chart_pref_x": 0.5,
		"chart_pref_y": 0.0,
		"color": "#90CAF9",
		"name": "machine_learning"
	}, {
		"id": 4,
		"chart_pref_x": 0.8,
		"chart_pref_y": 0.0,
		"color": "#80CBC4",
		"name": "data_science"
	}, {
		"id": 5,
		"chart_pref_x": 0.0,
		"chart_pref_y": 0.0,
		"color": "#CE93D8",
		"name": "probability"
	}, {
		"id": 6,
		"chart_pref_x": 0.5,
		"chart_pref_y": 0.0,
		"color": "#E57373",
		"name": "exploration"
	}, {
		"id": 7,
		"chart_pref_x": 0.8,
		"chart_pref_y": 0.0,
		"color": "#FFF176",
		"name": "lab"
	}],
	"cs_courses": [{
		"id": 74,
		"department_id": 2,
		"name": "Math 1A",
		"link": "/class_pages/template",
		"prereqs": [],
		"type_id": 1,
		"bias_x": 0,
		"bias_y": 0,
		"depth": 1.0,
		"startX": 432,
		"startY": 176
	}, {
		"id": 75,
		"department_id": 2,
		"name": "Math 1B",
		"link": "/class_pages/template",
		"prereqs": [{
			"id": 1,
			"course_id": 75,
			"prereq_id": 74,
			"is_recommended": false
		}],
		"type_id": 1,
		"bias_x": -50,
		"bias_y": 0,
		"depth": 2.0,
		"startX": 350,
		"startY": 261
	}, {
		"id": 76,
		"department_id": 2,
		"name": "Math 53",
		"link": "/class_pages/template",
		"prereqs": [{
			"id": 2,
			"course_id": 76,
			"prereq_id": 75,
			"is_recommended": false
		}],
		"type_id": 1,
		"bias_x": 50,
		"bias_y": 0,
		"depth": 2.0,
		"startX": 509,
		"startY": 255
	}, {
		"id": 77,
		"department_id": 2,
		"name": "Math 54",
		"link": "/class_pages/template",
		"prereqs": [{
			"id": 2,
			"course_id": 77,
			"prereq_id": 75,
			"is_recommended": false
		}],
		"type_id": 1,
		"bias_x": 0,
		"bias_y": 0,
		"depth": 5.0,
		"startX": 417,
		"startY": 632
	}, {
		"id": 2,
		"department_id": 2,
		"name": "Stat 134",
		"link": "/class_pages/template",
		"prereqs": [{
			"id": 4,
			"course_id": 2,
			"prereq_id": 76,
			"is_recommended": false
		}],
		"type_id": 2,
		"bias_x": 0,
		"bias_y": 0,
		"depth": 4.0,
		"startX": 765,
		"startY": 396
	}, {
		"id": 3,
		"department_id": 2,
		"name": "Stat 133",
		"link": "/class_pages/template",
		"prereqs": [{
			"id": 5,
			"course_id": 3,
			"prereq_id": 75,
			"is_recommended": false
		}],
		"type_id": 3,
		"bias_x": 0,
		"bias_y": 0,
		"depth": 3.0,
		"startX": 488,
		"startY": 406
	}, {
		"id": 287,
		"department_id": 2,
		"name": "Stat 135",
		"link": "/class_pages/template",
		"prereqs": [{
			"id": 6,
			"course_id": 287,
			"prereq_id": 76,
			"is_recommended": false
		}, {
			"id": 7,
			"course_id": 287,
			"prereq_id": 77,
			"is_recommended": false
		}],
		"type_id": 3,
		"bias_x": 0,
		"bias_y": 0,
		"depth": 3.0,
		"startX": 450,
		"startY": 471
	}, {
		"id": 4,
		"department_id": 2,
		"name": "Stat 158",
		"link": "/class_pages/template",
		"prereqs": [{
			"id": 8,
			"course_id": 4,
			"prereq_id": 75,
			"is_recommended": false
		}, {
			"id": 9,
			"course_id": 4,
			"prereq_id": 76,
			"is_recommended": false
		}, {
			"id": 10,
			"course_id": 4,
			"prereq_id": 77,
			"is_recommended": false
		}],
		"type_id": 3,
		"bias_x": 0,
		"bias_y": 0,
		"depth": 3.0,
		"startX": 385,
		"startY": 364
	}, {
		"id": 5,
		"department_id": 2,
		"name": "Stat 153",
		"link": "/class_pages/template",
		"prereqs": [{
			"id": 11,
			"course_id": 5,
			"prereq_id": 75,
			"is_recommended": false
		}, {
			"id": 12,
			"course_id": 5,
			"prereq_id": 76,
			"is_recommended": false
		}],
		"type_id": 3,
		"bias_x": 0,
		"bias_y": 0,
		"depth": 3.0,
		"startX": 383,
		"startY": 494
	}, {
		"id": 6,
		"department_id": 2,
		"name": "Stat 159",
		"link": "/class_pages/template",
		"prereqs": [{
			"id": 13,
			"course_id": 6,
			"prereq_id": 75,
			"is_recommended": false
		}, {
			"id": 14,
			"course_id": 6,
			"prereq_id": 76,
			"is_recommended": false
		}],
		"type_id": 3,
		"bias_x": 0,
		"bias_y": 0,
		"depth": 3.0,
		"startX": 460,
		"startY": 343
	}, {
		"id": 7,
		"department_id": 2,
		"name": "Stat 151A",
		"link": "/class_pages/template",
		"prereqs": [{
			"id": 16,
			"course_id": 7,
			"prereq_id": 75,
			"is_recommended": false
		}, {
			"id": 17,
			"course_id": 7,
			"prereq_id": 77,
			"is_recommended": false
		}],
		"type_id": 4,
		"bias_x": 0,
		"bias_y": 0,
		"depth": 3.0,
		"startX": 644,
		"startY": 351
	}, {
		"id": 8,
		"department_id": 2,
		"name": "Stat 157",
		"link": "/class_pages/template",
		"prereqs": [{
			"id": 18,
			"course_id": 8,
			"prereq_id": 7,
			"is_recommended": false
		}],
		"type_id": 4,
		"bias_x": 0,
		"bias_y": 0,
		"depth": 4.0,
		"startX": 643,
		"startY": 571
	}, {
		"id": 9,
		"department_id": 2,
		"name": "Stat 150",
		"link": "/class_pages/template",
		"prereqs": [{
			"id": 19,
			"course_id": 9,
			"prereq_id": 7,
			"is_recommended": false
		}],
		"type_id": 4,
		"bias_x": 0,
		"bias_y": 0,
		"depth": 4.0,
		"startX": 628,
		"startY": 471
	}, {
		"id": 394,
		"department_id": 2,
		"name": "Stat 152",
		"link": "/class_pages/template",
		"prereqs": [{
			"id": 20,
			"course_id": 394,
			"prereq_id": 7,
			"is_recommended": false
		}],
		"type_id": 4,
		"bias_x": 0,
		"bias_y": 0,
		"depth": 4.0,
		"startX": 580,
		"startY": 547
	}, {
		"id": 10,
		"department_id": 2,
		"name": "Stat 155",
		"link": "/class_pages/template",
		"prereqs": [{
			"id": 21,
			"course_id": 10,
			"prereq_id": 75,
			"is_recommended": false
		}],
		"type_id": 5,
		"bias_x": 0,
		"bias_y": 0,
		"depth": 3.0,
		"startX": 92,
		"startY": 403
	}, {
		"id": 11,
		"department_id": 2,
		"name": "Data 8",
		"link": "/class_pages/template",
		"prereqs": [{
			"id": 22,
			"course_id": 11,
			"prereq_id": 75,
			"is_recommended": false
		}, {
			"id": 23,
			"course_id": 11,
			"prereq_id": 76,
			"is_recommended": false
		}],
		"type_id": 5,
		"bias_x": 0,
		"bias_y": 0,
		"depth": 3.0,
		"startX": 144,
		"startY": 342
	}, {
		"id": 12,
		"department_id": 2,
		"name": "Data 100",
		"link": "/class_pages/template",
		"prereqs": [{
			"id": 24,
			"course_id": 12,
			"prereq_id": 75,
			"is_recommended": false
		}, {
			"id": 25,
			"course_id": 12,
			"prereq_id": 77,
			"is_recommended": false
		}, {
			"id": 26,
			"course_id": 12,
			"prereq_id": 7,
			"is_recommended": true
		}],
		"type_id": 5,
		"bias_x": 0,
		"bias_y": 0,
		"depth": 3.0,
		"startX": 158,
		"startY": 432
	}, {
		"id": 13,
		"department_id": 2,
		"name": "Data 102",
		"link": "/class_pages/template",
		"prereqs": [{
			"id": 27,
			"course_id": 13,
			"prereq_id": 12,
			"is_recommended": false
		}],
		"type_id": 5,
		"bias_x": 0,
		"bias_y": 0,
		"depth": 4.0,
		"startX": 140,
		"startY": 537
	}]
}